[
    {
      "CHK": "F",
      "INCID_ID": 17664837,
      "EXCP_CD": "0044",
      "EXCP_NM": "Floods",
      "NATN_CD": "JM",
      "LOC_CD": "JMMBJ",
      "LOC_NM": "MONTEGO BAY",
      "LTITDE": 18.48,
      "LNGTD": 282.08,
      "TITL_NM": "Heavy rainfall causes flash floods in Montego Bay, Jamaica",
      "SOURCE": "ⓒ Nationwideradiojm - Event researched by riskmethods",
      "CRT_DT_LOC": "2021-11-09 8:51",
      "VALID_DT_LOC": 20211112075959,
      "PROS_STAT_CD": "P",
      "FIX_YN": "N",
      "LOC_TOOLTIP": "",
      "VSL_NM": "[NULL]",
      "EXCEPT_NO": "[NULL]",
      "ATCH_FILE_NM": "[NULL]",
      "FILE_ROUT_NM": "[NULL]",
      "RESN_CONT_ORI": "Nationwideradiojm reports that:\nThe western city of Montego Bay and sections of the wider parish of",
      "RESN_CONT": "Nationwideradiojm reports that:\nThe western city of Montego Bay and sections of the wider parish of",
      "VIEW_YN" : "Y",
      "CNT" : "1"
    },
    {
      "CHK": "F",
      "INCID_ID": 17659986,
      "EXCP_CD": "0046",
      "EXCP_NM": "Civil Unrest",
      "NATN_CD": "DE",
      "LOC_CD": "DELEJ",
      "LOC_NM": "LEIPZIG",
      "LTITDE": 51.3453,
      "LNGTD": 12.3858,
      "TITL_NM": "Germany: Clashes reported at protest in central Leipzig",
      "SOURCE": "ⓒ GardaWorld - Event researched by riskmethods",
      "CRT_DT_LOC": "2021-11-07 11:59",
      "VALID_DT_LOC": 20211114075959,
      "PROS_STAT_CD": "P",
      "FIX_YN": "N",
      "LOC_TOOLTIP": "",
      "VSL_NM": "[NULL]",
      "EXCEPT_NO": "[NULL]",
      "ATCH_FILE_NM": "[NULL]",
      "FILE_ROUT_NM": "[NULL]",
      "RESN_CONT_ORI": "info: Radius 1 km from disaster place. GardaWorld reports that:\nActivists have staged a demonstrati",
      "RESN_CONT": "info: Radius 1 km from disaster place. GardaWorld reports that:\nActivists have staged a demonstrati",
      "VIEW_YN" : "Y",
      "CNT" : 1
    },
    {
      "CHK": "F",
      "INCID_ID": 17659265,
      "EXCP_CD": "0029",
      "EXCP_NM": "Infrastructure",
      "NATN_CD": "BA",
      "LOC_CD": "BASJJ",
      "LOC_NM": "SARAJEVO, BOSNIA AND HERZEGOVINA",
      "LTITDE": 43.85,
      "LNGTD": 18.38333333,
      "TITL_NM": "Floods in Bosnia cause blackouts in Sarajevo",
      "SOURCE": "ⓒ euronews - Event researched by riskmethods",
      "CRT_DT_LOC": "2021-11-06 21:00",
      "VALID_DT_LOC": 20211109075959,
      "PROS_STAT_CD": "F",
      "FIX_YN": "N",
      "LOC_TOOLTIP": "",
      "VSL_NM": "[NULL]",
      "EXCEPT_NO": "[NULL]",
      "ATCH_FILE_NM": "[NULL]",
      "FILE_ROUT_NM": "[NULL]",
      "RESN_CONT_ORI": "euronews reports that:\n<Inserted from Google Translate> Heavy rains have led to floods in Bosnia. F",
      "RESN_CONT": "euronews reports that:\n<Inserted from Google Translate> Heavy rains have led to floods in Bosnia. F",
      "VIEW_YN" : "Y",
      "CNT" : 1
    },
    {
      "CHK": "F",
      "INCID_ID": 17659264,
      "EXCP_CD": "ZZZZ",
      "EXCP_NM": "Etc",
      "NATN_CD": "PK",
      "LOC_CD": "PKLHE",
      "LOC_NM": "LAHORE",
      "LTITDE": 31.54,
      "LNGTD": 74.34,
      "TITL_NM": "(Update) Operational issues and shortage of planes continue at Allama Iqbal International Airport, Lahore, Pakistan",
      "SOURCE": "ⓒ Daily Times - Event researched by riskmethods",
      "CRT_DT_LOC": "2021-11-06 20:57",
      "VALID_DT_LOC": 20211113075959,
      "PROS_STAT_CD": "P",
      "FIX_YN": "N",
      "LOC_TOOLTIP": "",
      "VSL_NM": "[NULL]",
      "EXCEPT_NO": "[NULL]",
      "ATCH_FILE_NM": "[NULL]",
      "FILE_ROUT_NM": "[NULL]",
      "RESN_CONT_ORI": "Daily Times reports that:\nOn Saturday, another 17 flights were cancelled from Lahore’s Allama Iqbal",
      "RESN_CONT": "Daily Times reports that:\nOn Saturday, another 17 flights were cancelled from Lahore’s Allama Iqbal",
      "VIEW_YN" : "Y",
      "CNT" : 1
    },
    {
      "CHK": "F",
      "INCID_ID": 17654857,
      "EXCP_CD": "0033",
      "EXCP_NM": "Labor Dispute",
      "NATN_CD": "BD",
      "LOC_CD": "BDCGP",
      "LOC_NM": "CHITTAGONG, BANGLADESH",
      "LTITDE": 22.30556667,
      "LNGTD": 91.8002,
      "TITL_NM": "Transport strike hampers goods delivery activities at Chittagong Port in Bangladesh due to nationwide transport strike",
      "SOURCE": "ⓒ The Daily Star - Event researched by riskmethods",
      "CRT_DT_LOC": "2021-11-05 20:46",
      "VALID_DT_LOC": 20211112075959,
      "PROS_STAT_CD": "P",
      "FIX_YN": "N",
      "LOC_TOOLTIP": "",
      "VSL_NM": "[NULL]",
      "EXCEPT_NO": "[NULL]",
      "ATCH_FILE_NM": "[NULL]",
      "FILE_ROUT_NM": "[NULL]",
      "RESN_CONT_ORI": "The Daily Star reports that:\nThe delivery of imported goods from the Chittagong Port is being hampe",
      "RESN_CONT": "The Daily Star reports that:\nThe delivery of imported goods from the Chittagong Port is being hampe",
      "VIEW_YN" : "Y",
      "CNT" : 1
    },
    {
      "CHK": "F",
      "INCID_ID": 17654412,
      "EXCP_CD": "ZZZZ",
      "EXCP_NM": "Etc",
      "NATN_CD": "AU",
      "LOC_CD": "AUDRW",
      "LOC_NM": "DARWIN, AUSTRALIA",
      "LTITDE": 347.55,
      "LNGTD": 130.8333333,
      "TITL_NM": "(Update) Officials impose three-day lockdown in Greater Darwin area, Australia",
      "SOURCE": "ⓒ GardaWorld - Event researched by riskmethods",
      "CRT_DT_LOC": "2021-11-05 19:46",
      "VALID_DT_LOC": 20211112075959,
      "PROS_STAT_CD": "P",
      "FIX_YN": "N",
      "LOC_TOOLTIP": "",
      "VSL_NM": "[NULL]",
      "EXCEPT_NO": "[NULL]",
      "ATCH_FILE_NM": "[NULL]",
      "FILE_ROUT_NM": "[NULL]",
      "RESN_CONT_ORI": "GardaWorld reports that:\nNorthern Territory officials are enforcing a lockdown in Katherine, includ",
      "RESN_CONT": "GardaWorld reports that:\nNorthern Territory officials are enforcing a lockdown in Katherine, includ",
      "VIEW_YN" : "Y",
      "CNT" : 1
    },
    {
      "CHK": "F",
      "INCID_ID": 17654390,
      "EXCP_CD": "ZZZZ",
      "EXCP_NM": "Etc",
      "NATN_CD": "PH",
      "LOC_CD": "PHCGY",
      "LOC_NM": "CAGAYAN DE ORO- MINDANAO",
      "LTITDE": 8.49553333,
      "LNGTD": 124.6644167,
      "TITL_NM": "(Update) Curfew shortened in Cagayan de Oro as virus threat eases, Philippines",
      "SOURCE": "ⓒ INQUIRER.net - Event researched by riskmethods",
      "CRT_DT_LOC": "2021-11-05 16:49",
      "VALID_DT_LOC": 20211119075959,
      "PROS_STAT_CD": "P",
      "FIX_YN": "N",
      "LOC_TOOLTIP": "",
      "VSL_NM": "[NULL]",
      "EXCEPT_NO": "[NULL]",
      "ATCH_FILE_NM": "[NULL]",
      "FILE_ROUT_NM": "[NULL]",
      "RESN_CONT_ORI": "INQUIRER.net reports that:\nCagayan de Oro City Mayor Oscar Moreno has shortened the curfew period i",
      "RESN_CONT": "INQUIRER.net reports that:\nCagayan de Oro City Mayor Oscar Moreno has shortened the curfew period i",
      "VIEW_YN" : "Y",
      "CNT" : 1
    },
    {
      "CHK": "F",
      "INCID_ID": 17653954,
      "EXCP_CD": "0033",
      "EXCP_NM": "Labor Dispute",
      "NATN_CD": "IT",
      "LOC_CD": "ITAOI",
      "LOC_NM": "ANCONA",
      "LTITDE": 43.63333333,
      "LNGTD": 13.5,
      "TITL_NM": "Ancona International Airport workers plan strike on November 26, Italy",
      "SOURCE": "ⓒ Vivere SRL - Event researched by riskmethods",
      "CRT_DT_LOC": "2021-11-05 5:07",
      "VALID_DT_LOC": 20211111075959,
      "PROS_STAT_CD": "P",
      "FIX_YN": "N",
      "LOC_TOOLTIP": "",
      "VSL_NM": "[NULL]",
      "EXCEPT_NO": "[NULL]",
      "ATCH_FILE_NM": "[NULL]",
      "FILE_ROUT_NM": "[NULL]",
      "RESN_CONT_ORI": "Vivere Ancona reports that:\n<Inserted from Google Translate> On Wednesday, late in the evening, Anc",
      "RESN_CONT": "Vivere Ancona reports that:\n<Inserted from Google Translate> On Wednesday, late in the evening, Anc",
      "VIEW_YN" : "Y",
      "CNT" : 4
    },
    {
      "CHK": "F",
      "INCID_ID": 17653954,
      "EXCP_CD": "0033",
      "EXCP_NM": "Labor Dispute",
      "NATN_CD": "IT",
      "LOC_CD": "ITAOI",
      "LOC_NM": "ANCONA",
      "LTITDE": 16.18,
      "LNGTD": 81.13,
      "TITL_NM": "Ancona International Airport workers plan strike on November 26, Italy",
      "SOURCE": "ⓒ Vivere SRL - Event researched by riskmethods",
      "CRT_DT_LOC": "2021-11-05 5:07",
      "VALID_DT_LOC": 20211111075959,
      "PROS_STAT_CD": "P",
      "FIX_YN": "N",
      "LOC_TOOLTIP": "",
      "VSL_NM": "[NULL]",
      "EXCEPT_NO": "[NULL]",
      "ATCH_FILE_NM": "[NULL]",
      "FILE_ROUT_NM": "[NULL]",
      "RESN_CONT_ORI": "Vivere Ancona reports that:\n<Inserted from Google Translate> On Wednesday, late in the evening, Anc",
      "RESN_CONT": "Vivere Ancona reports that:\n<Inserted from Google Translate> On Wednesday, late in the evening, Anc",
      "VIEW_YN" : "N",
      "CNT" : 0
    },
    {
      "CHK": "F",
      "INCID_ID": 17653954,
      "EXCP_CD": "0033",
      "EXCP_NM": "Labor Dispute",
      "NATN_CD": "IT",
      "LOC_CD": "ITAOI",
      "LOC_NM": "ANCONA",
      "LTITDE": 14.2493,
      "LNGTD": 80.12246667,
      "TITL_NM": "Ancona International Airport workers plan strike on November 26, Italy",
      "SOURCE": "ⓒ Vivere SRL - Event researched by riskmethods",
      "CRT_DT_LOC": "2021-11-05 5:07",
      "VALID_DT_LOC": 20211111075959,
      "PROS_STAT_CD": "P",
      "FIX_YN": "N",
      "LOC_TOOLTIP": "",
      "VSL_NM": "[NULL]",
      "EXCEPT_NO": "[NULL]",
      "ATCH_FILE_NM": "[NULL]",
      "FILE_ROUT_NM": "[NULL]",
      "RESN_CONT_ORI": "Vivere Ancona reports that:\n<Inserted from Google Translate> On Wednesday, late in the evening, Anc",
      "RESN_CONT": "Vivere Ancona reports that:\n<Inserted from Google Translate> On Wednesday, late in the evening, Anc",
      "VIEW_YN" : "N",
      "CNT" : 0
    },
    {
      "CHK": "F",
      "INCID_ID": 17653726,
      "EXCP_CD": "ZZZZ",
      "EXCP_NM": "Etc",
      "NATN_CD": "PH",
      "LOC_CD": "PHMAN",
      "LOC_NM": "MANDAUE- CEBU",
      "LTITDE": 10.33333333,
      "LNGTD": 123.9333333,
      "TITL_NM": "Curfew still in effect in Mandaue City, Philippines",
      "SOURCE": "ⓒ Cebu Daily News - Event researched by riskmethods",
      "CRT_DT_LOC": "2021-11-04 21:16",
      "VALID_DT_LOC": 20211118075959,
      "PROS_STAT_CD": "P",
      "FIX_YN": "N",
      "LOC_TOOLTIP": "",
      "VSL_NM": "[NULL]",
      "EXCEPT_NO": "[NULL]",
      "ATCH_FILE_NM": "[NULL]",
      "FILE_ROUT_NM": "[NULL]",
      "RESN_CONT_ORI": "Cebu Daily News reports that:\nMandaue City has no plans yet to adjust or lift the city’s curfew, th",
      "RESN_CONT": "Cebu Daily News reports that:\nMandaue City has no plans yet to adjust or lift the city’s curfew, th",
      "VIEW_YN" : "Y",
      "CNT" : 0
    },
    {
      "CHK": "F",
      "INCID_ID": 17652314,
      "EXCP_CD": "ZZZZ",
      "EXCP_NM": "Etc",
      "NATN_CD": "PK",
      "LOC_CD": "PKLHE",
      "LOC_NM": "LAHORE",
      "LTITDE": 31.54,
      "LNGTD": 74.34,
      "TITL_NM": "(Update) Another 10 flights called off at Lahore Airport due to operational issues, Pakistan",
      "SOURCE": "ⓒ Daily Times - Event researched by riskmethods",
      "CRT_DT_LOC": "2021-11-04 4:26",
      "VALID_DT_LOC": 20211110075959,
      "PROS_STAT_CD": "P",
      "FIX_YN": "N",
      "LOC_TOOLTIP": "",
      "VSL_NM": "[NULL]",
      "EXCEPT_NO": "[NULL]",
      "ATCH_FILE_NM": "[NULL]",
      "FILE_ROUT_NM": "[NULL]",
      "RESN_CONT_ORI": "Daily Times reports that:\nOn Wednesday morning, another ten flights were called off due to operatio",
      "RESN_CONT": "Daily Times reports that:\nOn Wednesday morning, another ten flights were called off due to operatio",
      "VIEW_YN" : "Y",
      "CNT" : 0
    },
    {
      "CHK": "F",
      "INCID_ID": 17649012,
      "EXCP_CD": "0044",
      "EXCP_NM": "Floods",
      "NATN_CD": "ID",
      "LOC_CD": "IDPNK",
      "LOC_NM": "PONTIANAK- KALIMANTAN",
      "LTITDE": 359.97748,
      "LNGTD": 109.33031,
      "TITL_NM": "Central and West Kalimantan provinces affected by floods, Indonesia",
      "SOURCE": "ⓒ FloodList - Event researched by riskmethods",
      "CRT_DT_LOC": "2021-11-04 0:54",
      "VALID_DT_LOC": 20211106075959,
      "PROS_STAT_CD": "F",
      "FIX_YN": "N",
      "LOC_TOOLTIP": "",
      "VSL_NM": "[NULL]",
      "EXCEPT_NO": "[NULL]",
      "ATCH_FILE_NM": "[NULL]",
      "FILE_ROUT_NM": "[NULL]",
      "RESN_CONT_ORI": "FloodList reports that:\nAreas of Sekadau Regency in West Kalimantan Province have been flooded sinc",
      "RESN_CONT": "FloodList reports that:\nAreas of Sekadau Regency in West Kalimantan Province have been flooded sinc",
      "VIEW_YN" : "Y",
      "CNT" : 0
    },
    {
      "CHK": "F",
      "INCID_ID": 17653954,
      "EXCP_CD": "0033",
      "EXCP_NM": "Labor Dispute",
      "NATN_CD": "IT",
      "LOC_CD": "ITAOI",
      "LOC_NM": "ANCONA",
      "LTITDE": 28.68333333,
      "LNGTD": 342.2333333,
      "TITL_NM": "Ancona International Airport workers plan strike on November 26, Italy",
      "SOURCE": "ⓒ Vivere SRL - Event researched by riskmethods",
      "CRT_DT_LOC": "2021-11-05 5:07",
      "VALID_DT_LOC": 20211111075959,
      "PROS_STAT_CD": "P",
      "FIX_YN": "N",
      "LOC_TOOLTIP": "",
      "VSL_NM": "[NULL]",
      "EXCEPT_NO": "[NULL]",
      "ATCH_FILE_NM": "[NULL]",
      "FILE_ROUT_NM": "[NULL]",
      "RESN_CONT_ORI": "Vivere Ancona reports that:\n<Inserted from Google Translate> On Wednesday, late in the evening, Anc",
      "RESN_CONT": "Vivere Ancona reports that:\n<Inserted from Google Translate> On Wednesday, late in the evening, Anc",
      "VIEW_YN" : "N",
      "CNT" : 0
    },
    {
      "CHK": "F",
      "INCID_ID": 17648757,
      "EXCP_CD": "0045",
      "EXCP_NM": "Volcano",
      "NATN_CD": "ES",
      "LOC_CD": "ESSPC",
      "LOC_NM": "SANTA CRUZ DE LA PALMA",
      "LTITDE": 29.78333333,
      "LNGTD": 322.2333333,
      "TITL_NM": "(Update) Ash from erupting Cumbre Vieja volcano forces Spanish islanders indoors, La Palma",
      "SOURCE": "ⓒ Cox Media Group - Event researched by riskmethods",
      "CRT_DT_LOC": "2021-11-03 23:52",
      "VALID_DT_LOC": 20211110075959,
      "PROS_STAT_CD": "P",
      "FIX_YN": "N",
      "LOC_TOOLTIP": "",
      "VSL_NM": "[NULL]",
      "EXCEPT_NO": "[NULL]",
      "ATCH_FILE_NM": "[NULL]",
      "FILE_ROUT_NM": "[NULL]",
      "RESN_CONT_ORI": "102.3 KRMG reports that:\nAuthorities on the Spanish island of La Palma are telling people who live",
      "RESN_CONT": "102.3 KRMG reports that:\nAuthorities on the Spanish island of La Palma are telling people who live",
      "VIEW_YN" : "Y",
      "CNT" : 1
    }
  ]